dbx_dbutils_actor/__init__.py
dbx_dbutils_actor/dbx_dbutils_actor.py
dbx_dbutils_stub-0.1.2.dist-info/LICENCE
dbx_dbutils_stub-0.1.2.dist-info/METADATA
dbx_dbutils_stub-0.1.2.dist-info/WHEEL
dbx_dbutils_stub-0.1.2.dist-info/RECORD
