Metadata-Version: 2.1
Name: dbx-dbutils-stub
Version: 0.1.2
Summary: Stub for Databricks dbutils to enable VSCode linting
Author: francisco javier larios
Author-email: fjlsoto@gmail.com
Requires-Python: >=3.10,<4.0
Classifier: Programming Language :: Python :: 3
Classifier: Programming Language :: Python :: 3.10
Classifier: Programming Language :: Python :: 3.11
Classifier: Programming Language :: Python :: 3.12
